odoo8_addon_product_brand-8.0.0.1.0-py2.7-nspkg.pth
odoo8_addon_product_brand-8.0.0.1.0.dist-info/top_level.txt
odoo8_addon_product_brand-8.0.0.1.0.dist-info/WHEEL
odoo8_addon_product_brand-8.0.0.1.0.dist-info/RECORD
odoo8_addon_product_brand-8.0.0.1.0.dist-info/metadata.json
odoo8_addon_product_brand-8.0.0.1.0.dist-info/DESCRIPTION.rst
odoo8_addon_product_brand-8.0.0.1.0.dist-info/METADATA
odoo8_addon_product_brand-8.0.0.1.0.dist-info/namespace_packages.txt
odoo_addons/product_brand/product_brand_view.xml
odoo_addons/product_brand/__openerp__.py
odoo_addons/product_brand/product_brand.py
odoo_addons/product_brand/__init__.py
odoo_addons/product_brand/README.rst
odoo_addons/product_brand/security/ir.model.access.csv
odoo_addons/product_brand/i18n/fr_FR.po
odoo_addons/product_brand/i18n/product_brand.pot
odoo_addons/product_brand/i18n/fr.po
odoo_addons/product_brand/static/description/icon.png
